{"success": true, "error": null, "text": "Subtotal\n \u20b150.00\nTotal Quantity\n 1 items\nOrder Summary No.: ISOS000303249904\nDate Issued: 06/09/2023\nOrder ID: 230904E9FH3WU3\nOrder Paid Date: 06/09/2023\nPayment Method: Cash on Delivery\nSeller Name: FLOWER STATION\nSeller Address: Barangay 177, Caloocan City,\nMetro Manila, Metro Manila, 1400, Philippines\nBuyer Name: Dolores Constantino\nBuyer Address: Lipa City, Batangas\nOrder Details\nNo.\nProduct\nVariation\nProduct Price\nQty\nSubtotal\n1\nBubble Wrap 5 Meters Colored Heart Shape 20\"x 5mtrs for every quantity\nBABY PINK HEART,2\n0\"x5mtr Full No Cut\n\u20b150.00\n1\n\u20b150.00\nGrand Total\n\u20b153.00\nMerchandise Subtotal\n\u20b150.00\nShipping Fee\n\u20b158.00\nShipping Discount\n- \u20b155.00\nTotal amount in words\nFifty-Three Peso\nOrder Summary\n1 of 1\nEnd of Order Summary\nThis is a system generated document\nTHIS DOCUMENT IS NOT VALID FOR CLAIM OF INPUT TAX", "structured": {"date": "06/09/2023", "invoiceNumber": "Summary", "supplier": "FLOWER STATION", "sellerAddress": "Barangay 177, Caloocan City, Metro Manila, Metro Manila, 1400, Philippines", "buyerName": "Dolores Constantino", "buyerAddress": "Lipa City, Batangas", "total": 53.0, "currency": "PHP", "orderSummaryNo": "ISOS000303249904", "orderId": "230904E9FH3WU3", "dateIssued": "06/09/2023", "orderPaidDate": "06/09/2023", "paymentMethod": "Cash on Delivery", "merchandiseSubtotal": 50.0, "shippingFee": 58.0, "shippingDiscount": -55.0, "platformVoucher": 0.0, "amountInWords": 53.0, "items": [], "grandTotal": 53.0, "rawKeyValue": {"order summary no.": "ISOS000303249904", "date issued": "06/09/2023", "order id": "230904E9FH3WU3", "order paid date": "06/09/2023", "payment method": "Cash on Delivery", "seller name": "FLOWER STATION", "seller address": "Barangay 177, Caloocan City,", "buyer name": "Dolores Constantino", "buyer address": "Lipa City, Batangas", "fifty": "Three Peso"}}}
