{"success": true, "error": null, "text": "Subtotal\n \u20b141.00\nTotal Quantity\n 3 items\nOrder Summary No.: ISOS002056514637\nDate Issued: 31/07/2023\nOrder ID: 23072602PCX5BX\nOrder Paid Date: 31/07/2023\nPayment Method: Cash on Delivery\nSeller Name: CHK resin mold mall wholesale\nSeller Address: \u5e7f\u4e1c\u7701\u6df1\u5733\u5e02\u9f99\u5c97\u533a \u6df1\u5733\u5e02\u9f99\u5c97\u533a\n\u9f99\u5c97\u8857\u9053\u5357\u8054\u793e\u533a\u5218\u5c4b\u6751\u6625\u6c5f\u8def4\u53f7\u4e16\u76ca\u4e2d\u5fc3204\n518116\nBuyer Name: Dolores Constantino\nBuyer Address: Lipa City, Batangas\nOrder Details\nNo.\nProduct\nVariation\nProduct Price\nQty\nSubtotal\n1\nCHK 10-100g Hard UV Resin Glue Crystal Clear Ultraviolet Curing Epoxy Resi\nn Jewelry Making\n25g\n\u20b11.00\n1\n\u20b11.00\n2\nCHK 3mm Alphabet Letters Numbers Chunky Glitter Epoxy Resin Decorative\nStickers\nSILVER-A(1pcs\uff09\n\u20b120.00\n1\n\u20b120.00\n3\nCHK 3mm Alphabet Letters Numbers Chunky Glitter Epoxy Resin Decorative\nStickers\nSILVER-B(1pcs\uff09\n\u20b120.00\n1\n\u20b120.00\nGrand Total\n\u20b141.00\nMerchandise Subtotal\n\u20b141.00\nShipping Fee\n\u20b160.00\nShipping Discount\n- \u20b160.00\nTotal amount in words\nForty-One Peso\nOrder Summary\n1 of 1\nEnd of Order Summary\nThis is a system generated document\nTHIS DOCUMENT IS NOT VALID FOR CLAIM OF INPUT TAX", "structured": {"date": "31/07/2023", "invoiceNumber": "Summary", "supplier": "CHK resin mold mall wholesale", "sellerAddress": "\u5e7f\u4e1c\u7701\u6df1\u5733\u5e02\u9f99\u5c97\u533a \u6df1\u5733\u5e02\u9f99\u5c97\u533a \u9f99\u5c97\u8857\u9053\u5357\u8054\u793e\u533a\u5218\u5c4b\u6751\u6625\u6c5f\u8def4\u53f7\u4e16\u76ca\u4e2d\u5fc3204 518116", "buyerName": "Dolores Constantino", "buyerAddress": "Lipa City, Batangas", "total": 41.0, "currency": "PHP", "orderSummaryNo": "ISOS002056514637", "orderId": "23072602PCX5BX", "dateIssued": "31/07/2023", "orderPaidDate": "31/07/2023", "paymentMethod": "Cash on Delivery", "merchandiseSubtotal": 41.0, "shippingFee": 60.0, "shippingDiscount": -60.0, "platformVoucher": 0.0, "amountInWords": 41.0, "items": [], "grandTotal": 41.0, "rawKeyValue": {"order summary no.": "ISOS002056514637", "date issued": "31/07/2023", "order id": "23072602PCX5BX", "order paid date": "31/07/2023", "payment method": "Cash on Delivery", "seller name": "CHK resin mold mall wholesale", "seller address": "\u5e7f\u4e1c\u7701\u6df1\u5733\u5e02\u9f99\u5c97\u533a \u6df1\u5733\u5e02\u9f99\u5c97\u533a", "buyer name": "Dolores Constantino", "buyer address": "Lipa City, Batangas", "chk 10": "100g Hard UV Resin Glue Crystal Clear Ultraviolet Curing Epoxy Resi", "silver": "B(1pcs\uff09", "forty": "One Peso"}}}
